mypackage/__init__.py
mypackage/utils.py
rahaf_nabel-0.3.0.dist-info/licenses/LICENSE
rahaf_nabel-0.3.0.dist-info/METADATA
rahaf_nabel-0.3.0.dist-info/WHEEL
rahaf_nabel-0.3.0.dist-info/top_level.txt
rahaf_nabel-0.3.0.dist-info/RECORD
