Metadata-Version: 2.4
Name: Rahaf_nabel
Version: 0.3.0
Summary: باكيج بايثون بسيط يحتوي على دوال ترحيب وجمع 
Home-page: https://github.com/yourusername/mypackage
Author: Rahaf Nabel
Author-email: your.email@example.com
Classifier: Programming Language :: Python :: 3
Classifier: License :: OSI Approved :: MIT License
Classifier: Operating System :: OS Independent
Requires-Python: >=3.6
License-File: LICENSE
Dynamic: author
Dynamic: author-email
Dynamic: classifier
Dynamic: description-content-type
Dynamic: home-page
Dynamic: license-file
Dynamic: requires-python
Dynamic: summary
